{"EeWord":"k\u00FCllalt","EnWord":"sufficiently","EnWords":["enough","adequately"],"EnExplanation":"A term used to indicate that something is to a satisfactory extent or degree; it implies that there is enough of something to meet a requirement or need.","EeAudioUrl":"https://my1kee.blob.core.windows.net/audio/k\u00FCllalt.wav","Samples":[{"EeWord":"k\u00FCllalt","EeSentence":"Mul on k\u00FCllalt aega, et \u00F5ppida.","EnSentence":"I have enough time to study.","EeAudioUrl":"https://my1kee.blob.core.windows.net/audio/14cffc58-b6f1-4784-ba76-8f0d4e18f265.wav","ImageUrl":"https://my1kee.blob.core.windows.net/image/b96eac37-99ed-4054-be68-fb5696ba58ab.jpg"}]}