{"EeWord":"nelja","EnWord":"four","EnWords":["fourth"],"EnExplanation":"The word \u0027nelja\u0027 is the genitive form of \u0027neli\u0027, which means \u0027four\u0027 in English, and can also imply the fourth item in a sequence.","EeAudioUrl":"https://my1kee.blob.core.windows.net/audio/nelja.wav","Samples":[{"EeWord":"nelja","EeSentence":"Meil on neli \u00F5una lauas.","EnSentence":"We have four apples on the table.","EeAudioUrl":"https://my1kee.blob.core.windows.net/audio/2048c2c2-a05e-46b1-820f-05dfb5b44de3.wav","ImageUrl":"https://my1kee.blob.core.windows.net/image/167800d1-38f3-4d93-853c-0519cf5ecce1.jpg"}]}