{"EeWord":"varem","EnWord":"earlier","EnWords":["before","previously","formerly"],"EnExplanation":"The word refers to a time that is prior to the present moment or a specified time.","EeAudioUrl":"https://my1kee.blob.core.windows.net/audio/varem.wav","Samples":[{"EeWord":"varem","EeSentence":"Varem oli ilm soojem.","EnSentence":"Earlier, the weather was warmer.","EeAudioUrl":"https://my1kee.blob.core.windows.net/audio/95a99d5f-a590-474c-98af-91ce799e557c.wav","ImageUrl":"https://my1kee.blob.core.windows.net/image/78cbb35b-7c7e-4d05-b42c-0250341ee423.jpg"},{"EeWord":"varem","EeSentence":"Ma k\u00E4isin varem poes.","EnSentence":"I went to the store earlier.","EeAudioUrl":"https://my1kee.blob.core.windows.net/audio/0f91bb8e-580c-49b7-ba77-a2ba47f5e07a.wav","ImageUrl":"https://my1kee.blob.core.windows.net/image/7de48279-1c46-4714-84ed-f0fed2393ce8.jpg"}]}