{"EeWord":"v\u00E4ikese","EnWord":"small","EnWords":["little","tiny"],"EnExplanation":"The word \u0027v\u00E4ikese\u0027 is the genitive case of \u0027v\u00E4ike\u0027 in Estonian, which means \u0027small\u0027 or \u0027little\u0027. It refers to something that has a small size or quantity.","EeAudioUrl":"https://my1kee.blob.core.windows.net/audio/v\u00E4ikese.wav","Samples":[{"EeWord":"v\u00E4ikese","EeSentence":"Koer on v\u00E4ikese suurusega.","EnSentence":"The dog is of small size.","EeAudioUrl":"https://my1kee.blob.core.windows.net/audio/85fc07d5-bca2-4a45-b8ea-24daddd89b1b.wav","ImageUrl":"https://my1kee.blob.core.windows.net/image/c93e0f88-1231-4383-bfdd-81f978973b46.jpg"}]}